hasura_metadata_manager/__init__.py
hasura_metadata_manager/aggregate_expression/__init__.py
hasura_metadata_manager/aggregate_expression/aggregate_expression.py
hasura_metadata_manager/aggregate_expression/aggregate_expression_base.py
hasura_metadata_manager/aggregate_expression/aggregate_object_field.py
hasura_metadata_manager/aggregate_expression/aggregate_scalar_function.py
hasura_metadata_manager/aggregate_expression/data_connector_function_mapping.py
hasura_metadata_manager/auth_config/__init__.py
hasura_metadata_manager/auth_config/auth_config.py
hasura_metadata_manager/auth_config/auth_config_base.py
hasura_metadata_manager/base/__init__.py
hasura_metadata_manager/base/base.py
hasura_metadata_manager/base/core_base.py
hasura_metadata_manager/boolean_expression_type/__init__.py
hasura_metadata_manager/boolean_expression_type/boolean_expression_type.py
hasura_metadata_manager/boolean_expression_type/boolean_expression_type_base.py
hasura_metadata_manager/boolean_expression_type/boolean_expression_type_mapping.py
hasura_metadata_manager/boolean_expression_type/boolean_expression_type_operator.py
hasura_metadata_manager/boolean_expression_type/comparable_field.py
hasura_metadata_manager/boolean_expression_type/comparable_relationship.py
hasura_metadata_manager/boolean_expression_type/data_connector_operator_mapping.py
hasura_metadata_manager/command/__init__.py
hasura_metadata_manager/command/command.py
hasura_metadata_manager/command/command_argument.py
hasura_metadata_manager/command/command_base.py
hasura_metadata_manager/command/command_source_mapping.py
hasura_metadata_manager/command_permissions/__init__.py
hasura_metadata_manager/command_permissions/command_permission_preset.py
hasura_metadata_manager/command_permissions/command_permission_preset_base.py
hasura_metadata_manager/command_permissions/command_permissions.py
hasura_metadata_manager/command_permissions/command_permissions_base.py
hasura_metadata_manager/compatibility_config/__init__.py
hasura_metadata_manager-0.1.33.dist-info/METADATA
hasura_metadata_manager-0.1.33.dist-info/WHEEL
hasura_metadata_manager-0.1.33.dist-info/RECORD
